wf_family_survey/__init__.py
wf_family_survey/airtable.py
wf_family_survey/transparent_classroom.py
wf_family_survey-0.0.1.dist-info/LICENSE
wf_family_survey-0.0.1.dist-info/METADATA
wf_family_survey-0.0.1.dist-info/WHEEL
wf_family_survey-0.0.1.dist-info/top_level.txt
wf_family_survey-0.0.1.dist-info/RECORD
