Metadata-Version: 2.1
Name: wf-family-survey
Version: 0.0.1
Summary: Tools for working with Wildflower Schools family survey data
Home-page: https://github.com/WildflowerSchools/wf-family-survey
Author: Theodore Quinn
Author-email: ted.quinn@wildflowerschools.org
License: UNKNOWN
Keywords: survey
Platform: UNKNOWN
Classifier: Intended Audience :: Developers
Classifier: License :: OSI Approved :: MIT License
Classifier: Operating System :: OS Independent
Classifier: Programming Language :: Python
Requires-Dist: pandas (>=1.3)
Requires-Dist: wf-core-data-python (>=1.3)
